LICENSE
MANIFEST.in
README.md
setup.py
./README.md
Alphakit.egg-info/PKG-INFO
Alphakit.egg-info/SOURCES.txt
Alphakit.egg-info/dependency_links.txt
Alphakit.egg-info/requires.txt
Alphakit.egg-info/top_level.txt
alphakit/__init__.py
alphakit/const.c
alphakit/const.pyx
alphakit/data/__init__.py
alphakit/data/calculator.c
alphakit/data/calculator.pyx
alphakit/data/processing.c
alphakit/data/processing.pyx
alphakit/factor/__init__.py
alphakit/factor/analysis.c
alphakit/factor/analysis.pyx
alphakit/factor/metrics.c
alphakit/factor/metrics.pyx
alphakit/factor/processing.c
alphakit/factor/processing.pyx
alphakit/factor/transform.c
alphakit/factor/transform.pyx
alphakit/portfolio/__init__.py
alphakit/portfolio/combine.c
alphakit/portfolio/combine.pyx
alphakit/portfolio/metrics.c
alphakit/portfolio/metrics.pyx
alphakit/portfolio/optimize.c
alphakit/portfolio/optimize.pyx
requirements/py3.txt