Metadata-Version: 2.1
Name: Alphakit
Version: 1.3.0
Summary: Alphakit 1.3.0
Home-page: https://github.com/flaght
Author: flaght
Author-email: flaght@gmail.com
License-File: LICENSE
